redhat_assisted_installer/__init__.py
redhat_assisted_installer/assisted_installer.py
redhat_assisted_installer/lib/utils.py
redhat_assisted_installer/lib/schema/cluster.py
redhat_assisted_installer/lib/schema/infra_env.py
redhat_assisted_installer/lib/schema/schema.py
redhat_assisted_installer-0.4.5.dist-info/METADATA
redhat_assisted_installer-0.4.5.dist-info/WHEEL
redhat_assisted_installer-0.4.5.dist-info/RECORD
