Metadata-Version: 2.3
Name: redhat-assisted-installer
Version: 0.4.5
Summary: Python module to implement the RedHat Assisted Installer API
Project-URL: Homepage, https://github.com/JustinBatchelor/redhat-assisted-installer
Project-URL: Issues, https://github.com/JustinBatchelor/redhat-assisted-installer/issues
Author-email: Justin Batchelor <justinrossbatchelor@gmail.com>
Classifier: License :: OSI Approved :: MIT License
Classifier: Operating System :: OS Independent
Classifier: Programming Language :: Python :: 3
Requires-Python: >=3.12
